setup.cfg
setup.py
papimem/__init__.py
papimem/app.py
papimem/cli.py
papimem/proxy.py
papimem.egg-info/PKG-INFO
papimem.egg-info/SOURCES.txt
papimem.egg-info/dependency_links.txt
papimem.egg-info/entry_points.txt
papimem.egg-info/not-zip-safe
papimem.egg-info/requires.txt
papimem.egg-info/top_level.txt
papimem/storage/__init__.py
papimem/storage/base.py
papimem/storage/redis.py
papimem/web/__init__.py
papimem/web/views.py
papimem/web/templates/index.html