Metadata-Version: 1.0
Name: papimem
Version: 0.1.3
Summary: Python API Request-Response Memorizer
Home-page: https://github.com/czekan/papimem
Author: Tomasz Czekanski
Author-email: t.czekanski@gmail.com
License: GPL
Keywords: memorize requests,api cache,proxy,analyze request-response
Platform: UNKNOWN
